jsonable_llm/__init__.py
jsonable_llm-0.0.1.dev0.dist-info/METADATA
jsonable_llm-0.0.1.dev0.dist-info/WHEEL
jsonable_llm-0.0.1.dev0.dist-info/top_level.txt
jsonable_llm-0.0.1.dev0.dist-info/RECORD
