Metadata-Version: 2.1
Name: jsonable_llm
Version: 0.0.1.dev0
Summary: Make 7B/13B LLM output JSON more stable
Home-page: https://github.com/gusye1234/jsonable-llm
Author: JianbaiYe
Classifier: Programming Language :: Python :: 3
Classifier: License :: OSI Approved :: MIT License
Classifier: Operating System :: OS Independent
Requires-Python: >=3.9
Requires-Dist: pydantic
